docstring_composer/__init__.py
docstring_composer/cli.py
docstring_composer/composer.py
docstring_composer/schema.py
docstring_composer/ds_schema/__init__.py
docstring_composer/ds_schema/docstring_schema.py
docstring_composer/formatters/__init__.py
docstring_composer/formatters/all_formatters.py
docstring_composer/formatters/c_doxygen.py
docstring_composer/formatters/cpp_doxygen.py
docstring_composer/formatters/csharp_xmldoc.py
docstring_composer/formatters/go_godoc.py
docstring_composer/formatters/java_javadoc.py
docstring_composer/formatters/js_jsdoc.py
docstring_composer/formatters/kotlin_kdoc.py
docstring_composer/formatters/php_phpdoc.py
docstring_composer/formatters/python_epydoc.py
docstring_composer/formatters/python_google.py
docstring_composer/formatters/python_numpy.py
docstring_composer/formatters/python_rest.py
docstring_composer/formatters/python_sphinx.py
docstring_composer/formatters/ruby_yard.py
docstring_composer/tests/__init__.py
docstring_composer/tests/test_formatters.py
docstring_composer/utils/__init__.py
docstring_composer/utils/text.py
docstring_composer-0.1.3.dist-info/licenses/LICENSE
docstring_composer-0.1.3.dist-info/METADATA
docstring_composer-0.1.3.dist-info/WHEEL
docstring_composer-0.1.3.dist-info/entry_points.txt
docstring_composer-0.1.3.dist-info/top_level.txt
docstring_composer-0.1.3.dist-info/RECORD
